poautofill/__init__.py
poautofill/flycheck_poautofill.py
poautofill/poautofill.py
poautofill-0.1.3.dist-info/METADATA
poautofill-0.1.3.dist-info/WHEEL
poautofill-0.1.3.dist-info/entry_points.txt
poautofill-0.1.3.dist-info/top_level.txt
poautofill-0.1.3.dist-info/RECORD
