Metadata-Version: 2.1
Name: poautofill
Version: 0.1.3
Summary: Autofill po files with automated translations.
Home-page: https://github.com/JulienPalard/poautofill
Author: Julien Palard
Author-email: julien@palard.fr
License: MIT license
Keywords: poautofill
Platform: UNKNOWN
Classifier: Development Status :: 2 - Pre-Alpha
Classifier: Intended Audience :: Developers
Classifier: License :: OSI Approved :: MIT License
Classifier: Natural Language :: English
Classifier: Programming Language :: Python :: 3
Classifier: Programming Language :: Python :: 3.4
Classifier: Programming Language :: Python :: 3.5
Classifier: Programming Language :: Python :: 3.6
Requires-Dist: polib
Requires-Dist: requests
Requires-Dist: click
Provides-Extra: dev
Requires-Dist: black; extra == 'dev'
Requires-Dist: detox; extra == 'dev'
